mazesforprogrammers/__init__.py
mazesforprogrammers/algorithms/__init__.py
mazesforprogrammers/algorithms/algorithm.py
mazesforprogrammers/algorithms/binary_tree.py
mazesforprogrammers/algorithms/sidewinder.py
mazesforprogrammers/base/__init__.py
mazesforprogrammers/base/cell.py
mazesforprogrammers/base/grid.py
mazesforprogrammers_lib-0.1.2.dist-info/LICENSE
mazesforprogrammers_lib-0.1.2.dist-info/METADATA
mazesforprogrammers_lib-0.1.2.dist-info/WHEEL
mazesforprogrammers_lib-0.1.2.dist-info/top_level.txt
mazesforprogrammers_lib-0.1.2.dist-info/RECORD
