Metadata-Version: 2.1
Name: mazesforprogrammers-lib
Version: 0.1.2
Summary: A package implementing mazes for programmers in Python3 based on Mazes for Programmers by Jamis Buck
Home-page: https://github.com/Wigginns/mazes-for-programmers
Author: Benjamin Cowley
License: UNKNOWN
Project-URL: Bug Tracker, https://github.com/Wigginns/mazes-for-programmers/issues
Platform: UNKNOWN
Classifier: Development Status :: 1 - Planning
Classifier: Programming Language :: Python :: 3
Classifier: License :: OSI Approved :: The Unlicense (Unlicense)
Classifier: Operating System :: OS Independent
Requires-Python: >=3.6
License-File: LICENSE
